simple_html_table/__init__.py
simple_html_table/htmltable.py
simple_html_table-0.2.0.dist-info/LICENSE
simple_html_table-0.2.0.dist-info/METADATA
simple_html_table-0.2.0.dist-info/WHEEL
simple_html_table-0.2.0.dist-info/top_level.txt
simple_html_table-0.2.0.dist-info/RECORD
