Metadata-Version: 2.1
Name: simple-html-table
Version: 0.2.0
Summary: Simple way to create HTML tables with support for rowspan and colspan attributes.
Author-email: Gavin Burnell <g.burnell@leeds.ac.uk>
License: MIT
Project-URL: Homepage, https://github.com/gb119/simple_html_table
Keywords: html,table
Classifier: Programming Language :: Python :: 3
Requires-Python: >=3.7
License-File: LICENSE
Requires-Dist: numpy
